{"credit":"Made with Blockbench","texture_size":[32,32],"textures":{"1":"ia:629","3":"ia:646","particle":"#1"},"elements":[{"from":[7.3,-1.99289,7.3],"to":[8.7,-0.59289,8.7],"rotation":{"angle":-45,"axis":"x","origin":[8,-1.29289,8]},"faces":{"north":{"uv":[6,12,6.75,12.75],"texture":"#3"},"east":{"uv":[12,11.5,12.75,12.25],"texture":"#3"},"south":{"uv":[12.5,1.5,13.25,2.25],"texture":"#3"},"west":{"uv":[2,12.5,2.75,13.25],"texture":"#3"},"up":{"uv":[13.25,3.25,12.5,2.5],"texture":"#3"},"down":{"uv":[3.75,12.5,3,13.25],"texture":"#3"}}},{"from":[7.5,-1.04289,7.5],"to":[8.5,-0.04289,8.5],"rotation":{"angle":0,"axis":"y","origin":[7.5,-1.04289,7.5]},"faces":{"north":{"uv":[9.5,4,10,4.5],"texture":"#3"},"east":{"uv":[12.5,4.5,13,5],"texture":"#3"},"south":{"uv":[13,8.5,13.5,9],"texture":"#3"},"west":{"uv":[13.5,4,14,4.5],"texture":"#3"}}},{"from":[7.5,7.70711,7.5],"to":[8.5,9.95711,8.5],"rotation":{"angle":0,"axis":"y","origin":[8,7.70711,8]},"faces":{"north":{"uv":[11,11.5,11.5,12.75],"texture":"#3"},"east":{"uv":[11.5,11.5,12,12.75],"texture":"#3"},"south":{"uv":[0,12,0.5,13.25],"texture":"#3"},"west":{"uv":[0.5,12,1,13.25],"texture":"#3"},"down":{"uv":[2.5,14.5,2,15],"texture":"#3"}}},{"from":[7.6,5.45711,7.6],"to":[8.4,7.70711,8.4],"rotation":{"angle":0,"axis":"y","origin":[8,7.70711,8]},"faces":{"north":{"uv":[1,12,1.5,13.25],"texture":"#3"},"east":{"uv":[1.5,12,2,13.25],"texture":"#3"},"south":{"uv":[5,12,5.5,13.25],"texture":"#3"},"west":{"uv":[5.5,12,6,13.25],"texture":"#3"}}},{"from":[7.35,9.95711,7.35],"to":[8.65,10.45711,8.65],"rotation":{"angle":0,"axis":"y","origin":[8,7.70711,8]},"faces":{"north":{"uv":[14.5,10.5,15.25,10.75],"texture":"#3"},"east":{"uv":[13,14.5,13.75,14.75],"texture":"#3"},"south":{"uv":[14,14.5,14.75,14.75],"texture":"#3"},"west":{"uv":[0,15,0.75,15.25],"texture":"#3"},"up":{"uv":[13.25,4.25,12.5,3.5],"texture":"#3"},"down":{"uv":[4.75,12.5,4,13.25],"texture":"#3"}}},{"from":[7.35,4.95711,7.35],"to":[8.65,5.45711,8.65],"rotation":{"angle":0,"axis":"y","origin":[8,5.20711,8]},"faces":{"north":{"uv":[1,15,1.75,15.25],"texture":"#3"},"east":{"uv":[15,1.5,15.75,1.75],"texture":"#3"},"south":{"uv":[2,15,2.75,15.25],"texture":"#3"},"west":{"uv":[15,2,15.75,2.25],"texture":"#3"},"up":{"uv":[7.75,13.25,7,12.5],"texture":"#3"},"down":{"uv":[8.75,12.5,8,13.25],"texture":"#3"}}},{"from":[7.25,16.05,8],"to":[8.75,18.05,10],"rotation":{"angle":-45,"axis":"x","origin":[7.5,16.05,8]},"faces":{"north":{"uv":[11.5,1.5,12.25,2.5],"texture":"#3"},"east":{"uv":[3,10.5,4,11.5],"texture":"#3"},"south":{"uv":[2,11.5,2.75,12.5],"texture":"#3"},"west":{"uv":[4,10.5,5,11.5],"texture":"#3"},"up":{"uv":[12.25,3.5,11.5,2.5],"texture":"#3"},"down":{"uv":[3.75,11.5,3,12.5],"texture":"#3"}}},{"from":[7,16.3,8.25],"to":[9,17.8,9.75],"rotation":{"angle":-45,"axis":"x","origin":[7.5,16.05,8]},"faces":{"north":{"uv":[11.5,3.5,12.5,4.25],"texture":"#3"},"east":{"uv":[9,12.5,9.75,13.25],"texture":"#3"},"south":{"uv":[4,11.5,5,12.25],"texture":"#3"},"west":{"uv":[12.5,9,13.25,9.75],"texture":"#3"},"up":{"uv":[8,12.25,7,11.5],"texture":"#3"},"down":{"uv":[9,11.5,8,12.25],"texture":"#3"}}},{"from":[7.5,18.01924,6.18413],"to":[8.5,19.01924,7.68413],"rotation":{"angle":22.5,"axis":"x","origin":[8,19.33032,5.38461]},"faces":{"north":{"uv":[2.5,14.5,3,15],"texture":"#3"},"east":{"uv":[9,10.5,9.75,11],"texture":"#3"},"west":{"uv":[11.5,4.5,12.25,5],"texture":"#3"},"up":{"uv":[14.5,4.75,14,4],"texture":"#3"},"down":{"uv":[14.5,5,14,5.75],"texture":"#3"}}},{"from":[7.585,18.46,5.3775],"to":[8.415,19.29,6.6225],"rotation":{"angle":45,"axis":"x","origin":[8,19.33032,5.38461]},"faces":{"north":{"uv":[3,14.5,3.5,15],"texture":"#3"},"east":{"uv":[14.5,3,15,3.5],"texture":"#3"},"west":{"uv":[3.5,14.5,4,15],"texture":"#3"},"up":{"uv":[15,4,14.5,3.5],"texture":"#3"},"down":{"uv":[4.5,14.5,4,15],"texture":"#3"}}},{"from":[7.67215,19.00956,4.63996],"to":[8.32785,19.99311,5.29566],"rotation":{"angle":-22.5,"axis":"x","origin":[8,19.33032,5.38461]},"faces":{"north":{"uv":[15,6,15.25,6.5],"texture":"#3"},"east":{"uv":[6.5,15,6.75,15.5],"texture":"#3"},"south":{"uv":[15,6.5,15.25,7],"texture":"#3"},"west":{"uv":[7,15,7.25,15.5],"texture":"#3"},"up":{"uv":[6.25,15.75,6,15.5],"texture":"#3"}}},{"from":[7.72133,19.63516,4.46412],"to":[8.27867,20.47118,5.02147],"rotation":{"angle":0,"axis":"y","origin":[8,19.33032,5.38461]},"faces":{"north":{"uv":[15,7,15.25,7.5],"texture":"#3"},"east":{"uv":[7.5,15,7.75,15.5],"texture":"#3"},"south":{"uv":[15,7.5,15.25,8],"texture":"#3"},"west":{"uv":[8,15,8.25,15.5],"texture":"#3"},"up":{"uv":[15.75,6.25,15.5,6],"texture":"#3"}}},{"from":[7.77985,19.99466,4.12803],"to":[8.22015,20.65511,4.56833],"rotation":{"angle":22.5,"axis":"x","origin":[8,19.33032,5.38461]},"faces":{"north":{"uv":[6.5,15.5,6.75,15.75],"texture":"#3"},"east":{"uv":[15.5,6.5,15.75,6.75],"texture":"#3"},"south":{"uv":[7,15.5,7.25,15.75],"texture":"#3"},"west":{"uv":[15.5,7,15.75,7.25],"texture":"#3"},"up":{"uv":[7.75,15.75,7.5,15.5],"texture":"#3"}}},{"from":[7.5,18.01924,8.31587],"to":[8.5,19.01924,9.81587],"rotation":{"angle":-22.5,"axis":"x","origin":[8,19.33032,10.61539]},"faces":{"east":{"uv":[14,6,14.75,6.5],"texture":"#3"},"south":{"uv":[9.5,14.5,10,15],"texture":"#3"},"west":{"uv":[14,6.5,14.75,7],"texture":"#3"},"up":{"uv":[14.5,7.75,14,7],"texture":"#3"},"down":{"uv":[11.5,14,11,14.75],"texture":"#3"}}},{"from":[7.585,18.46,9.3775],"to":[8.415,19.29,10.6225],"rotation":{"angle":-45,"axis":"x","origin":[8,19.33032,10.61539]},"faces":{"east":{"uv":[8,14.5,8.5,15],"texture":"#3"},"south":{"uv":[8.5,14.5,9,15],"texture":"#3"},"west":{"uv":[14.5,8.5,15,9],"texture":"#3"},"up":{"uv":[9.5,15,9,14.5],"texture":"#3"},"down":{"uv":[15,9,14.5,9.5],"texture":"#3"}}},{"from":[7.67215,19.00956,10.70434],"to":[8.32785,19.99311,11.36004],"rotation":{"angle":22.5,"axis":"x","origin":[8,19.33032,10.61539]},"faces":{"north":{"uv":[2.5,15.5,2.75,16],"texture":"#3"},"east":{"uv":[3,15.5,3.25,16],"texture":"#3"},"south":{"uv":[3.5,15.5,3.75,16],"texture":"#3"},"west":{"uv":[4,15.5,4.25,16],"texture":"#3"},"up":{"uv":[15.75,9.25,15.5,9],"texture":"#3"}}},{"from":[7.77985,19.99466,11.43167],"to":[8.22015,20.65511,11.87197],"rotation":{"angle":-22.5,"axis":"x","origin":[8,19.33032,10.61539]},"faces":{"north":{"uv":[8,15.5,8.25,15.75],"texture":"#3"},"east":{"uv":[15.5,8,15.75,8.25],"texture":"#3"},"south":{"uv":[8.5,15.5,8.75,15.75],"texture":"#3"},"west":{"uv":[15.5,8.5,15.75,8.75],"texture":"#3"},"up":{"uv":[9.25,15.75,9,15.5],"texture":"#3"}}},{"from":[7.72133,19.63516,10.97853],"to":[8.27867,20.47118,11.53588],"rotation":{"angle":0,"axis":"y","origin":[8,19.33032,10.61539]},"faces":{"north":{"uv":[1,15.5,1.25,16],"texture":"#3"},"east":{"uv":[15.5,1,15.75,1.5],"texture":"#3"},"south":{"uv":[1.5,15.5,1.75,16],"texture":"#3"},"west":{"uv":[2,15.5,2.25,16],"texture":"#3"},"up":{"uv":[15.75,7.75,15.5,7.5],"texture":"#3"}}},{"from":[7.5,20.65,7.5],"to":[8.5,21.15,8.5],"rotation":{"angle":0,"axis":"y","origin":[7.5,20.65,7.5]},"faces":{"north":{"uv":[15,8,15.5,8.25],"texture":"#3"},"east":{"uv":[8.5,15,9,15.25],"texture":"#3"},"south":{"uv":[15,8.5,15.5,8.75],"texture":"#3"},"west":{"uv":[9,15,9.5,15.25],"texture":"#3"}}},{"from":[7.5,23.15,7.5],"to":[8.5,23.65,8.5],"rotation":{"angle":0,"axis":"y","origin":[7.5,23.15,7.5]},"faces":{"north":{"uv":[15,9,15.5,9.25],"texture":"#3"},"east":{"uv":[9.5,15,10,15.25],"texture":"#3"},"south":{"uv":[15,9.5,15.5,9.75],"texture":"#3"},"west":{"uv":[10,15,10.5,15.25],"texture":"#3"},"up":{"uv":[15,4.5,14.5,4],"texture":"#3"}}},{"from":[7.25,21.15,7.25],"to":[8.75,23.15,8.75],"rotation":{"angle":0,"axis":"y","origin":[7.5,21.65,7.5]},"faces":{"north":{"uv":[9,11.5,9.75,12.5],"texture":"#3"},"east":{"uv":[11.5,9,12.25,10],"texture":"#3"},"south":{"uv":[10,11.5,10.75,12.5],"texture":"#3"},"west":{"uv":[11.5,10,12.25,11],"texture":"#3"},"up":{"uv":[10.75,13.25,10,12.5],"texture":"#3"},"down":{"uv":[13.25,10,12.5,10.75],"texture":"#3"}}},{"from":[7.57,22.335,5.97],"to":[8.43,22.765,6.83],"rotation":{"angle":-22.5,"axis":"x","origin":[8,21.725,6.4]},"faces":{"north":{"uv":[15,11.5,15.5,11.75],"texture":"#3"},"east":{"uv":[15,12,15.5,12.25],"texture":"#3"},"south":{"uv":[15,12.5,15.5,12.75],"texture":"#3"},"west":{"uv":[13,15,13.5,15.25],"texture":"#3"},"up":{"uv":[5,15,4.5,14.5],"texture":"#3"}}},{"from":[7.355,20.865,5.755],"to":[8.645,22.335,7.045],"rotation":{"angle":-22.5,"axis":"x","origin":[8,21.725,6.4]},"faces":{"north":{"uv":[12,12.5,12.75,13.25],"texture":"#3"},"east":{"uv":[13,4.5,13.75,5.25],"texture":"#3"},"south":{"uv":[13,5.5,13.75,6.25],"texture":"#3"},"west":{"uv":[6,13,6.75,13.75],"texture":"#3"},"up":{"uv":[13.75,7.25,13,6.5],"texture":"#3"},"down":{"uv":[13.75,7.5,13,8.25],"texture":"#3"}}},{"from":[7.57,20.435,5.97],"to":[8.43,20.865,6.83],"rotation":{"angle":-22.5,"axis":"x","origin":[8,21.725,6.4]},"faces":{"north":{"uv":[15,10,15.5,10.25],"texture":"#3"},"east":{"uv":[10.5,15,11,15.25],"texture":"#3"},"south":{"uv":[11,15,11.5,15.25],"texture":"#3"},"west":{"uv":[15,11,15.5,11.25],"texture":"#3"}}},{"from":[7.57,22.335,9.17],"to":[8.43,22.765,10.03],"rotation":{"angle":22.5,"axis":"x","origin":[8,21.725,9.6]},"faces":{"north":{"uv":[15,14,15.5,14.25],"texture":"#3"},"east":{"uv":[14.5,15,15,15.25],"texture":"#3"},"south":{"uv":[15,14.5,15.5,14.75],"texture":"#3"},"west":{"uv":[15,15,15.5,15.25],"texture":"#3"},"up":{"uv":[15,5,14.5,4.5],"texture":"#3"}}},{"from":[7.355,20.865,8.955],"to":[8.645,22.335,10.245],"rotation":{"angle":22.5,"axis":"x","origin":[8,21.725,9.6]},"faces":{"north":{"uv":[11,13,11.75,13.75],"texture":"#3"},"east":{"uv":[13,11,13.75,11.75],"texture":"#3"},"south":{"uv":[13,12,13.75,12.75],"texture":"#3"},"west":{"uv":[13,13,13.75,13.75],"texture":"#3"},"up":{"uv":[0.75,14.25,0,13.5],"texture":"#3"},"down":{"uv":[14.25,0,13.5,0.75],"texture":"#3"}}},{"from":[7.57,20.435,9.17],"to":[8.43,20.865,10.03],"rotation":{"angle":22.5,"axis":"x","origin":[8,21.725,9.6]},"faces":{"north":{"uv":[15,13,15.5,13.25],"texture":"#3"},"east":{"uv":[13.5,15,14,15.25],"texture":"#3"},"south":{"uv":[15,13.5,15.5,13.75],"texture":"#3"},"west":{"uv":[14,15,14.5,15.25],"texture":"#3"}}},{"from":[7.985,21.00779,3.84857],"to":[8.005,22.00779,5.34857],"rotation":{"angle":45,"axis":"x","origin":[7.995,21.50779,4.59857]},"faces":{"east":{"uv":[13.5,10.5,14.25,11],"texture":"#3"},"west":{"uv":[6,14,6.75,14.5],"texture":"#3"}}},{"from":[7.985,21.00779,10.65143],"to":[8.005,22.00779,12.15143],"rotation":{"angle":-45,"axis":"x","origin":[7.995,21.50779,11.40143]},"faces":{"east":{"uv":[14,8,14.75,8.5],"texture":"#3"},"west":{"uv":[14,11,14.75,11.5],"texture":"#3"}}},{"from":[6.25,18.2,6.25],"to":[9.75,19.2,9.75],"rotation":{"angle":0,"axis":"y","origin":[6.5,18.2,6.5]},"faces":{"north":{"uv":[7,10.5,8.75,11],"texture":"#3"},"east":{"uv":[11,5,12.75,5.5],"texture":"#3"},"south":{"uv":[11,5.5,12.75,6],"texture":"#3"},"west":{"uv":[11,6,12.75,6.5],"texture":"#3"},"down":{"uv":[7.75,2,6,3.75],"texture":"#3"}}},{"from":[6,19.2,6],"to":[10,20.7,10],"rotation":{"angle":0,"axis":"y","origin":[6.5,19.2,6.5]},"faces":{"north":{"uv":[0,9.5,2,10.25],"texture":"#3"},"east":{"uv":[2,9.5,4,10.25],"texture":"#3"},"south":{"uv":[9.5,3,11.5,3.75],"texture":"#3"},"west":{"uv":[8,9.5,10,10.25],"texture":"#3"},"up":{"uv":[6,2,4,0],"texture":"#3"},"down":{"uv":[6,2,4,4],"texture":"#3"}}},{"from":[6.21185,20.62365,6.5],"to":[6.24185,22.12365,9.5],"rotation":{"angle":22.5,"axis":"z","origin":[6.22685,21.39865,8]},"faces":{"east":{"uv":[10,9,11.5,9.75],"texture":"#3"},"west":{"uv":[10,10,11.5,10.75],"texture":"#3"}}},{"from":[9.75815,20.62365,6.5],"to":[9.78815,22.12365,9.5],"rotation":{"angle":-22.5,"axis":"z","origin":[9.77315,21.39865,8]},"faces":{"east":{"uv":[0,10.5,1.5,11.25],"texture":"#3"},"west":{"uv":[1.5,10.5,3,11.25],"texture":"#3"}}},{"from":[7.4,17.95239,4.43933],"to":[7.4,19.45239,5.93933],"rotation":{"angle":-45,"axis":"x","origin":[7.4,18.70239,5.18933]},"faces":{"west":{"uv":[1,13.5,1.75,14.25],"texture":"#3"}}},{"from":[7.4,17.95239,10.06067],"to":[7.4,19.45239,11.56067],"rotation":{"angle":45,"axis":"x","origin":[7.4,18.70239,10.81067]},"faces":{"west":{"uv":[13.5,2,14.25,2.75],"texture":"#3"}}},{"from":[7.5,19.7566,4.11968],"to":[7.5,20.7566,5.11968],"rotation":{"angle":22.5,"axis":"x","origin":[7.5,20.2566,4.61968]},"faces":{"west":{"uv":[5,14.5,5.5,15],"texture":"#3"}}},{"from":[7.5,19.7566,10.88032],"to":[7.5,20.7566,11.88032],"rotation":{"angle":-22.5,"axis":"x","origin":[7.5,20.2566,11.38032]},"faces":{"west":{"uv":[14.5,9.5,15,10],"texture":"#3"}}},{"from":[8.5,19.7566,10.88032],"to":[8.5,20.7566,11.88032],"rotation":{"angle":-22.5,"axis":"x","origin":[8.5,20.2566,11.38032]},"faces":{"east":{"uv":[10,14.5,10.5,15],"texture":"#3"}}},{"from":[8.6,17.95239,10.06067],"to":[8.6,19.45239,11.56067],"rotation":{"angle":45,"axis":"x","origin":[8.6,18.70239,10.81067]},"faces":{"east":{"uv":[13.5,3,14.25,3.75],"texture":"#3"}}},{"from":[8.5,19.7566,4.11968],"to":[8.5,20.7566,5.11968],"rotation":{"angle":22.5,"axis":"x","origin":[8.5,20.2566,4.61968]},"faces":{"east":{"uv":[14.5,7.5,15,8],"texture":"#3"}}},{"from":[8.6,17.95239,4.43933],"to":[8.6,19.45239,5.93933],"rotation":{"angle":-45,"axis":"x","origin":[8.6,18.70239,5.18933]},"faces":{"east":{"uv":[3,13.5,3.75,14.25],"texture":"#3"}}},{"from":[7.5,10.45711,7.5],"to":[8.5,10.95711,8.5],"rotation":{"angle":0,"axis":"y","origin":[8,10.95711,8]},"faces":{"north":{"uv":[0,15.5,0.5,15.75],"texture":"#3"},"east":{"uv":[15.5,0,16,0.25],"texture":"#3"},"south":{"uv":[0.5,15.5,1,15.75],"texture":"#3"},"west":{"uv":[15.5,0.5,16,0.75],"texture":"#3"},"up":{"uv":[15,5.5,14.5,5],"texture":"#3"},"down":{"uv":[6,14.5,5.5,15],"texture":"#3"}}},{"from":[7.5,4.45711,7.5],"to":[8.5,4.95711,8.5],"rotation":{"angle":0,"axis":"y","origin":[8,4.95711,8]},"faces":{"north":{"uv":[4.5,15.5,5,15.75],"texture":"#3"},"east":{"uv":[15.5,4.5,16,4.75],"texture":"#3"},"south":{"uv":[15.5,5,16,5.25],"texture":"#3"},"west":{"uv":[5.5,15.5,6,15.75],"texture":"#3"},"up":{"uv":[15,10.5,14.5,10],"texture":"#3"},"down":{"uv":[11,14.5,10.5,15],"texture":"#3"}}},{"from":[7.5,15.95711,7.5],"to":[8.5,16.95711,8.5],"rotation":{"angle":0,"axis":"y","origin":[8,16.45711,8]},"faces":{"north":{"uv":[14.5,5.5,15,6],"texture":"#3"},"east":{"uv":[6,14.5,6.5,15],"texture":"#3"},"south":{"uv":[6.5,14.5,7,15],"texture":"#3"},"west":{"uv":[7,14.5,7.5,15],"texture":"#3"},"up":{"uv":[15,7.5,14.5,7],"texture":"#3"},"down":{"uv":[8,14.5,7.5,15],"texture":"#3"}}},{"from":[7.35,10.95711,7.35],"to":[8.65,15.95711,8.65],"rotation":{"angle":0,"axis":"y","origin":[8,17.20711,8]},"faces":{"north":{"uv":[4,8,4.75,10.5],"texture":"#3"},"east":{"uv":[8,4.5,8.75,7],"texture":"#3"},"south":{"uv":[5,8,5.75,10.5],"texture":"#3"},"west":{"uv":[6,8,6.75,10.5],"texture":"#3"},"up":{"uv":[14.25,1.75,13.5,1],"texture":"#3"},"down":{"uv":[2.75,13.5,2,14.25],"texture":"#3"}}},{"from":[7.35,-0.04289,7.35],"to":[8.65,4.45711,8.65],"rotation":{"angle":0,"axis":"y","origin":[8,6.20711,8]},"faces":{"north":{"uv":[7,8,7.75,10.25],"texture":"#3"},"east":{"uv":[8,7,8.75,9.25],"texture":"#3"},"south":{"uv":[9,4.5,9.75,6.75],"texture":"#3"},"west":{"uv":[9,7,9.75,9.25],"texture":"#3"},"up":{"uv":[4.75,14.25,4,13.5],"texture":"#3"},"down":{"uv":[5.75,13.5,5,14.25],"texture":"#3"}}},{"from":[7.985,16.74221,9.90143],"to":[8.005,17.74221,11.40143],"rotation":{"angle":22.5,"axis":"x","origin":[7.995,17.24221,10.65143]},"faces":{"east":{"uv":[14,12.5,14.75,13],"texture":"#3"},"west":{"uv":[13,14,13.75,14.5],"texture":"#3"}}},{"from":[7.985,16.74221,4.59857],"to":[8.005,17.74221,6.09857],"rotation":{"angle":-22.5,"axis":"x","origin":[7.995,17.24221,5.34857]},"faces":{"east":{"uv":[14,11.5,14.75,12],"texture":"#3"},"west":{"uv":[14,12,14.75,12.5],"texture":"#3"}}},{"from":[6.25,16.25,-0.5],"to":[9.75,17.25,3],"rotation":{"angle":0,"axis":"x","origin":[7.95,20.35382,-6.23858]},"faces":{"north":{"uv":[11,6.5,12.75,7],"texture":"#3"},"east":{"uv":[7,11,8.75,11.5],"texture":"#3"},"south":{"uv":[11,7,12.75,7.5],"texture":"#3"},"west":{"uv":[11,7.5,12.75,8],"texture":"#3"},"down":{"uv":[5.75,6,4,7.75],"texture":"#3"}}},{"from":[6.25,22.75,-0.5],"to":[9.75,23.75,3],"rotation":{"angle":0,"axis":"x","origin":[7.95,20.35382,-6.23858]},"faces":{"north":{"uv":[0,11.5,1.75,12],"texture":"#3"},"east":{"uv":[11.5,0,13.25,0.5],"texture":"#3"},"south":{"uv":[11.5,0.5,13.25,1],"texture":"#3"},"west":{"uv":[11.5,1,13.25,1.5],"texture":"#3"},"up":{"uv":[7.75,7.75,6,6],"texture":"#3"}}},{"from":[6,17.25,-0.75],"to":[10,22.75,3.25],"rotation":{"angle":0,"axis":"x","origin":[7.95,20.35382,-6.23858]},"faces":{"north":{"uv":[0,0,2,2.75],"texture":"#3"},"east":{"uv":[2,0,4,2.75],"texture":"#3"},"south":{"uv":[0,3,2,5.75],"texture":"#3"},"west":{"uv":[2,3,4,5.75],"texture":"#3"},"up":{"uv":[6,6,4,4],"texture":"#3"},"down":{"uv":[2,6,0,8],"texture":"#3"}}},{"from":[5.99784,17.25,12.72716],"to":[9.99784,20.25,16.72716],"rotation":{"angle":0,"axis":"y","origin":[7.95,20.35382,8.73858]},"faces":{"north":{"uv":[10,1.5,8,3],"texture":"#3"},"east":{"uv":[10,0,8,1.5],"texture":"#3"},"south":{"uv":[2,8,0,9.5],"texture":"#3"},"west":{"uv":[4,8,2,9.5],"texture":"#3"},"up":{"uv":[8,0,6,2],"texture":"#3"},"down":{"uv":[4,8,2,6],"texture":"#3"}}},{"from":[6.24784,16.25,12.97716],"to":[9.74784,17.25,16.47716],"rotation":{"angle":0,"axis":"y","origin":[7.95,20.35382,8.73858]},"faces":{"north":{"uv":[10.75,11,9,11.5],"texture":"#3"},"east":{"uv":[12.75,8.5,11,9],"texture":"#3"},"south":{"uv":[12.75,8,11,8.5],"texture":"#3"},"west":{"uv":[12.75,11,11,11.5],"texture":"#3"},"down":{"uv":[7.75,5.75,6,4],"texture":"#3"}}},{"from":[6.49784,20.25,13.22716],"to":[9.49784,22.25,16.22716],"rotation":{"angle":0,"axis":"y","origin":[7.95,20.35382,8.73858]},"faces":{"north":{"uv":[11.5,2,10,3],"texture":"#3"},"east":{"uv":[11.5,1,10,2],"texture":"#3"},"south":{"uv":[11.5,0,10,1],"texture":"#3"},"west":{"uv":[11.5,4,10,5],"texture":"#3"},"up":{"uv":[9.5,3,8,4.5],"texture":"#3"}}},{"from":[8.74784,19.75,15.47716],"to":[10.24784,20.75,16.97716],"rotation":{"angle":0,"axis":"y","origin":[7.95,20.35382,8.73858]},"faces":{"north":{"uv":[14.75,14,14,14.5],"texture":"#3"},"east":{"uv":[14.75,13.5,14,14],"texture":"#3"},"south":{"uv":[14.75,13,14,13.5],"texture":"#3"},"west":{"uv":[0.75,14.5,0,15],"texture":"#3"},"up":{"uv":[7.75,13.5,7,14.25],"texture":"#3"},"down":{"uv":[8.75,14.25,8,13.5],"texture":"#3"}}},{"from":[5.74784,19.75,15.47716],"to":[7.24784,20.75,16.97716],"rotation":{"angle":0,"axis":"y","origin":[7.95,20.35382,8.73858]},"faces":{"north":{"uv":[1.75,14.5,1,15],"texture":"#3"},"east":{"uv":[15.25,0.5,14.5,1],"texture":"#3"},"south":{"uv":[15.25,0,14.5,0.5],"texture":"#3"},"west":{"uv":[15.25,1,14.5,1.5],"texture":"#3"},"up":{"uv":[14.25,9.5,13.5,10.25],"texture":"#3"},"down":{"uv":[10.75,14.25,10,13.5],"texture":"#3"}}},{"from":[6.96303,22.10272,14.22716],"to":[8.46303,24.60272,14.72716],"rotation":{"angle":22.5,"axis":"z","origin":[7.95,20.35382,8.73858]},"faces":{"north":{"uv":[6.75,10.5,6,11.75],"texture":"#3"},"east":{"uv":[11.75,14,11.5,15.25],"texture":"#3"},"south":{"uv":[5.75,10.5,5,11.75],"texture":"#3"},"west":{"uv":[14.75,1.5,14.5,2.75],"texture":"#3"},"up":{"uv":[15.75,2.5,15,2.75],"texture":"#3"},"down":{"uv":[3.75,15.25,3,15],"texture":"#3"}}},{"from":[6.96303,23.10272,15.22716],"to":[8.46303,24.60272,15.72716],"rotation":{"angle":22.5,"axis":"z","origin":[7.95,20.35382,8.73858]},"faces":{"north":{"uv":[9.75,13.5,9,14.25],"texture":"#3"},"east":{"uv":[15.25,4.5,15,5.25],"texture":"#3"},"south":{"uv":[14.25,8.5,13.5,9.25],"texture":"#3"},"west":{"uv":[5.25,15,5,15.75],"texture":"#3"},"up":{"uv":[6.25,15,5.5,15.25],"texture":"#3"},"down":{"uv":[15.75,5.75,15,5.5],"texture":"#3"}}},{"from":[6.96303,24.10272,14.72716],"to":[8.46303,24.60272,15.22716],"rotation":{"angle":22.5,"axis":"z","origin":[7.95,20.35382,8.73858]},"faces":{"east":{"uv":[9.75,15.5,9.5,15.75],"texture":"#3"},"west":{"uv":[15.75,9.5,15.5,9.75],"texture":"#3"},"up":{"uv":[4.75,15,4,15.25],"texture":"#3"},"down":{"uv":[15.75,4.25,15,4],"texture":"#3"}}},{"from":[7.52536,22.13933,14.22716],"to":[9.02536,26.13933,14.72716],"rotation":{"angle":-22.5,"axis":"z","origin":[7.95,20.35382,8.73858]},"faces":{"north":{"uv":[10.75,7,10,9],"texture":"#3"},"east":{"uv":[12.25,13.5,12,15.5],"texture":"#3"},"south":{"uv":[10.75,5,10,7],"texture":"#3"},"west":{"uv":[12.75,13.5,12.5,15.5],"texture":"#3"},"up":{"uv":[15.75,3,15,3.25],"texture":"#3"},"down":{"uv":[15.75,3.75,15,3.5],"texture":"#3"}}},{"from":[1.5,16.7,7.99],"to":[5,23.3,8.01],"rotation":{"angle":-45,"axis":"y","origin":[8,22.97492,8]},"faces":{"north":{"uv":[7,0,0,13],"texture":"#1"},"south":{"uv":[0,0,7,13],"texture":"#1"}}},{"from":[1.5,16.7,7.99],"to":[5,23.3,8.01],"rotation":{"angle":45,"axis":"y","origin":[8,22.97492,8]},"faces":{"north":{"uv":[7,0,0,13],"texture":"#1"},"south":{"uv":[0,0,7,13],"texture":"#1"}}},{"from":[11,16.7,7.99],"to":[14.5,23.3,8.01],"rotation":{"angle":-45,"axis":"y","origin":[8,22.97492,8]},"faces":{"north":{"uv":[0,0,7,13],"texture":"#1"},"south":{"uv":[7,0,0,13],"texture":"#1"}}},{"from":[11,16.7,7.99],"to":[14.5,23.3,8.01],"rotation":{"angle":45,"axis":"y","origin":[8,22.97492,8]},"faces":{"north":{"uv":[0,0,7,13],"texture":"#1"},"south":{"uv":[7,0,0,13],"texture":"#1"}}}],"gui_light":"front","display":{"thirdperson_righthand":{"translation":[0,-1.75,1]},"thirdperson_lefthand":{"translation":[0,-1.75,1]},"firstperson_righthand":{"rotation":[-20,0,0],"translation":[3.75,-3,-2.5]},"firstperson_lefthand":{"rotation":[-20,0,0],"translation":[3.75,-3,-2.5]},"ground":{"rotation":[45,0,0],"translation":[0,5,0],"scale":[0.7,0.7,0.7]},"gui":{"rotation":[-90,45,90],"translation":[3,-3,0],"scale":[0.7,0.7,0.7]},"head":{"rotation":[0,-90,0]},"fixed":{"rotation":[0,-90,0],"translation":[0,-3.75,-2.75],"scale":[2,2,2]}}}