{"format_version":"1.9.0","credit":"Made with Blockbench","texture_size":[128,128],"textures":{"1":"ia:263","particle":"ia:263"},"elements":[{"from":[5,0,5],"to":[11,16,11],"rotation":{"angle":0,"axis":"y","origin":[6,-5,6]},"faces":{"north":{"uv":[7.5,4.5,9,8.5],"texture":"#1"},"east":{"uv":[7.5,4.5,9,8.5],"texture":"#1"},"south":{"uv":[7.5,4.5,9,8.5],"texture":"#1"},"west":{"uv":[7.5,4.5,9,8.5],"texture":"#1"}}}],"gui_light":"front","display":{"thirdperson_righthand":{"rotation":[75,45,0],"translation":[0,2.5,1.5],"scale":[0.3,0.3,0.3]},"thirdperson_lefthand":{"rotation":[75,45,0],"translation":[0,2.5,1.5],"scale":[0.3,0.3,0.3]},"firstperson_righthand":{"rotation":[0,120,0],"translation":[0,2.75,0],"scale":[0.3,0.3,0.3]},"firstperson_lefthand":{"rotation":[0,120,0],"translation":[0,2.75,0],"scale":[0.3,0.3,0.3]},"ground":{"translation":[0,10,0],"scale":[0.3,0.3,0.3]},"gui":{"rotation":[25,155,0],"translation":[0,-0.75,0],"scale":[0.6,0.6,0.6]},"fixed":{"rotation":[-90,0,0],"translation":[0,0,-14],"scale":[2,2,2]}},"groups":[{"name":"group10","origin":[7.5,-6.5,7.5],"color":0,"children":[0]}],"mcmodels":"27154b2f074063c4cac6d092c7293801"}