{"credit":"Made by Nog's Menagerie","texture_size":[32,32],"textures":{"0":"ia:219","particle":"ia:219"},"elements":[{"name":"head","from":[6,0,0],"to":[10,3,4],"rotation":{"angle":0,"axis":"y","origin":[8,3,1]},"faces":{"north":{"uv":[9.5,10.5,11.5,12],"texture":"#0"},"east":{"uv":[2.5,11,4.5,12.5],"texture":"#0"},"south":{"uv":[5,11.5,7,13],"texture":"#0"},"west":{"uv":[0,12,2,13.5],"texture":"#0"},"up":{"uv":[9,11,7,9],"texture":"#0"},"down":{"uv":[2,9.5,0,11.5],"texture":"#0"}}},{"name":"torso","from":[5,0,4],"to":[11,2,12],"rotation":{"angle":0,"axis":"y","origin":[8,2,7.5]},"faces":{"north":{"uv":[12,4,15,5],"texture":"#0"},"east":{"uv":[2.5,9.5,6.5,10.5],"texture":"#0"},"south":{"uv":[12,5.5,15,6.5],"texture":"#0"},"west":{"uv":[9.5,9,13.5,10],"texture":"#0"},"up":{"uv":[3,9,0,5],"texture":"#0"},"down":{"uv":[6.5,5,3.5,9],"texture":"#0"}}},{"name":"torso","from":[4,2,4],"to":[12,5,13],"rotation":{"angle":0,"axis":"y","origin":[8,2,7.5]},"faces":{"north":{"uv":[9,0,13,1.5],"texture":"#0"},"east":{"uv":[7,5,11.5,6.5],"texture":"#0"},"south":{"uv":[9,2,13,3.5],"texture":"#0"},"west":{"uv":[7,7,11.5,8.5],"texture":"#0"},"up":{"uv":[4,4.5,0,0],"texture":"#0"},"down":{"uv":[8.5,0,4.5,4.5],"texture":"#0"}}},{"name":"left_arm","from":[1.17855,0.009,5.35936],"to":[5.17855,1.009,7.35936],"rotation":{"angle":-22.5,"axis":"y","origin":[8.5,2.0045,6.52855]},"faces":{"north":{"uv":[9,4,11,4.5],"texture":"#0"},"east":{"uv":[13.5,1,14.5,1.5],"texture":"#0"},"south":{"uv":[9,12.5,11,13],"texture":"#0"},"west":{"uv":[13.5,2,14.5,2.5],"texture":"#0"},"up":{"uv":[14,8,12,7],"texture":"#0"},"down":{"uv":[14,10.5,12,11.5],"texture":"#0"}}},{"name":"left_leg","from":[4.80621,0.009,11.0417],"to":[6.80621,1.009,15.0417],"rotation":{"angle":-22.5,"axis":"y","origin":[4.60621,0.509,12.4417]},"faces":{"north":{"uv":[13.5,3,14.5,3.5],"texture":"#0"},"east":{"uv":[2.5,13,4.5,13.5],"texture":"#0"},"south":{"uv":[5,13.5,6,14],"texture":"#0"},"west":{"uv":[13.5,0,15.5,0.5],"texture":"#0"},"up":{"uv":[8.5,13.5,7.5,11.5],"texture":"#0"},"down":{"uv":[13,12,12,14],"texture":"#0"}}},{"name":"right_arm","from":[10.82145,0.009,5.35936],"to":[14.82145,1.009,7.35936],"rotation":{"angle":22.5,"axis":"y","origin":[7.5,2.0045,6.52855]},"faces":{"north":{"uv":[11,4,9,4.5],"texture":"#0"},"east":{"uv":[14.5,2,13.5,2.5],"texture":"#0"},"south":{"uv":[11,12.5,9,13],"texture":"#0"},"west":{"uv":[14.5,1,13.5,1.5],"texture":"#0"},"up":{"uv":[12,8,14,7],"texture":"#0"},"down":{"uv":[12,10.5,14,11.5],"texture":"#0"}}},{"name":"right_leg","from":[9.19379,0.009,11.0417],"to":[11.19379,1.009,15.0417],"rotation":{"angle":22.5,"axis":"y","origin":[11.39379,0.509,12.4417]},"faces":{"north":{"uv":[14.5,3,13.5,3.5],"texture":"#0"},"east":{"uv":[15.5,0,13.5,0.5],"texture":"#0"},"south":{"uv":[6,13.5,5,14],"texture":"#0"},"west":{"uv":[4.5,13,2.5,13.5],"texture":"#0"},"up":{"uv":[7.5,13.5,8.5,11.5],"texture":"#0"},"down":{"uv":[12,12,13,14],"texture":"#0"}}}],"gui_light":"front","display":{"thirdperson_righthand":{"rotation":[82,13,0],"translation":[0,0,1.75],"scale":[0.6,0.6,0.6]},"thirdperson_lefthand":{"rotation":[82,13,0],"translation":[0,0,1.75],"scale":[0.6,0.6,0.6]},"firstperson_righthand":{"rotation":[0,109,5],"translation":[2.5,7.75,0],"scale":[0.71,0.71,0.71]},"firstperson_lefthand":{"rotation":[0,109,5],"translation":[2.5,7.75,0],"scale":[0.71,0.71,0.71]},"ground":{"translation":[0,3.5,0],"scale":[0.65,0.65,0.65]},"gui":{"rotation":[25,151,0],"translation":[0.25,4.5,0],"scale":[0.85,0.85,0.85]},"head":{"translation":[0,14.4,0]},"fixed":{"rotation":[-90,0,0],"translation":[0,0,-13.5],"scale":[1.7,1.7,1.7]}},"groups":[{"name":"base","origin":[8,8,8],"color":0,"children":[{"name":"group","origin":[8,2.0045,6.85355],"color":0,"children":[0]},1,2,{"name":"group","origin":[8,2.0045,6.85355],"color":0,"children":[3,4,5,6]}]}],"mcmodels":"1b748cc4559679cbdac17560a74316a3"}