{"credit":"Made with Blockbench","texture_size":[32,32],"textures":{"1":"ia:372","particle":"#1"},"elements":[{"from":[2,0,4],"to":[14,7,12],"faces":{"north":{"uv":[6,0,12,3.5],"texture":"#1"},"east":{"uv":[0,11,4,14.5],"texture":"#1"},"south":{"uv":[6,3.5,12,7],"texture":"#1"},"west":{"uv":[12,0,16,3.5],"texture":"#1"},"up":{"uv":[6,4,0,0],"texture":"#1"},"down":{"uv":[6,4,0,8],"texture":"#1"}}},{"from":[3,7,5],"to":[13,13,11],"faces":{"north":{"uv":[6,7,11,10],"texture":"#1"},"east":{"uv":[11,7,14,10],"texture":"#1"},"south":{"uv":[0,8,5,11],"texture":"#1"},"west":{"uv":[12,3.5,15,6.5],"texture":"#1"},"up":{"uv":[10,13,5,10],"texture":"#1"},"down":{"uv":[15,10,10,13],"texture":"#1"}}}],"display":{"thirdperson_righthand":{"rotation":[75,45,0],"translation":[0,2.5,0],"scale":[0.375,0.375,0.375]},"thirdperson_lefthand":{"rotation":[75,45,0],"translation":[0,2.5,0],"scale":[0.375,0.375,0.375]},"firstperson_righthand":{"rotation":[0,45,0],"scale":[0.4,0.4,0.4]},"firstperson_lefthand":{"rotation":[0,225,0],"scale":[0.4,0.4,0.4]},"ground":{"translation":[0,3,0],"scale":[0.25,0.25,0.25]},"gui":{"rotation":[30,225,0],"scale":[0.625,0.625,0.625]},"head":{"translation":[0,-48.5,0],"scale":[1.62,1.62,1.62]},"fixed":{"scale":[0.5,0.5,0.5]}},"gui_light":"front"}